{
  "ComponentIndexes": {
    "Component1": 16,
    "Component1_1": 17,
    "SoyCandleImage": 18
  },
  "ControlUniqueGuids": {},
  "ControlUniqueIds": {
    "Account_Settings": 185,
    "Add_Item_To_Inventory": 186,
    "Add_to_cart": 89,
    "addItem": 46,
    "App": 1,
    "Arrow2": 178,
    "Arrow2_2": 19,
    "BarcodeScanner1": 257,
    "Body1": 27,
    "Body1_1": 82,
    "Body1_2": 83,
    "Body1_3": 84,
    "Body4": 158,
    "Body4_1": 159,
    "Body4_2": 160,
    "BrowseGallery": 31,
    "BrowseGallery1": 22,
    "BrowseGallery1_1": 79,
    "BrowseGallery1_2": 245,
    "Browsing Gallery": 30,
    "Button1": 280,
    "Button11": 8,
    "Button11_1": 7,
    "Button11_2": 12,
    "Button11_3": 11,
    "Button2": 183,
    "Button2_1": 269,
    "Button3": 142,
    "Button3_1": 88,
    "Button4": 252,
    "Button4_1": 253,
    "Button5": 166,
    "Button6": 164,
    "Button6_1": 165,
    "Button7": 39,
    "Button8": 233,
    "Button9": 234,
    "Cart": 145,
    "Component1": 5,
    "Component1_1": 9,
    "Customer Home Page": 239,
    "Customer page": 237,
    "Customer_Sign_Up": 265,
    "DataCardKey10": 134,
    "DataCardKey12": 128,
    "DataCardKey13": 131,
    "DataCardKey14": 137,
    "DataCardKey38": 100,
    "DataCardKey39": 105,
    "DataCardKey40": 110,
    "DataCardKey43": 118,
    "DataCardKey44": 115,
    "DataCardKey60": 199,
    "DataCardKey61": 204,
    "DataCardKey62": 214,
    "DataCardKey63": 209,
    "DataCardKey65": 219,
    "DataCardKey69": 194,
    "DataCardValue10": 135,
    "DataCardValue12": 129,
    "DataCardValue13": 132,
    "DataCardValue14": 138,
    "DataCardValue38": 101,
    "DataCardValue39": 106,
    "DataCardValue40": 111,
    "DataCardValue43": 119,
    "DataCardValue44": 116,
    "DataCardValue60": 200,
    "DataCardValue61": 205,
    "DataCardValue62": 215,
    "DataCardValue63": 210,
    "DataCardValue65": 220,
    "DataCardValue69": 195,
    "Description_DataCard10": 197,
    "Description_DataCard12": 117,
    "Description_DataCard2": 133,
    "Employee Menu": 40,
    "Employee page": 238,
    "Employee_Sign_Up": 175,
    "ErrorMessage26": 102,
    "ErrorMessage27": 107,
    "ErrorMessage28": 112,
    "ErrorMessage49": 201,
    "ErrorMessage50": 206,
    "ErrorMessage51": 216,
    "ErrorMessage52": 211,
    "ErrorMessage54": 221,
    "ErrorMessage55": 196,
    "FirstScreen": 235,
    "Form1": 126,
    "Form6": 98,
    "Form8": 191,
    "Gallery1": 53,
    "Gallery1_1": 65,
    "Gallery2": 152,
    "Gallery5": 223,
    "galleryTemplate1": 23,
    "galleryTemplate1_1": 80,
    "galleryTemplate1_2": 246,
    "galleryTemplate2": 54,
    "galleryTemplate2_1": 66,
    "galleryTemplate3": 153,
    "galleryTemplate5": 32,
    "galleryTemplate6": 224,
    "Group1": 184,
    "Group2": 264,
    "Group3": 174,
    "Icon1": 52,
    "Icon1_1": 64,
    "Icon10": 258,
    "Icon10_1": 91,
    "Icon10_2": 168,
    "Icon11": 241,
    "Icon11_1": 76,
    "Icon11_2": 149,
    "Icon12": 144,
    "Icon14": 157,
    "Icon2": 254,
    "Icon3": 268,
    "Icon4": 275,
    "Icon5": 279,
    "Icon6": 243,
    "Icon6_1": 43,
    "Icon7": 75,
    "Icon7_1": 148,
    "Icon8": 259,
    "Icon8_2": 92,
    "Icon8_3": 169,
    "Icon9": 260,
    "Icon9_2": 93,
    "Icon9_3": 170,
    "IconAccept2": 190,
    "IconAccept3": 123,
    "IconCancel2": 188,
    "IconCancel3": 121,
    "IconNewItem1": 18,
    "IconRefresh1": 15,
    "IconSortUpDown1": 17,
    "Image_DataCard2": 127,
    "Image1": 267,
    "Image1_1": 74,
    "Image1_3": 147,
    "Image1_4": 177,
    "Image1_5": 42,
    "Image2": 55,
    "Image2_1": 67,
    "Image3": 236,
    "Image4": 4,
    "Image6": 33,
    "Image7": 225,
    "Image8": 78,
    "Image9": 155,
    "Inventory": 13,
    "ItemName_DataCard10": 202,
    "ItemName_DataCard2": 130,
    "ItemWanted": 124,
    "Label1": 143,
    "Label1_1": 266,
    "Label1_10": 41,
    "Label1_11": 61,
    "Label1_12": 49,
    "Label1_2": 240,
    "Label1_3": 256,
    "Label1_4": 176,
    "Label1_6": 73,
    "Label1_7": 90,
    "Label1_8": 146,
    "Label1_9": 167,
    "Label10": 255,
    "Label11": 141,
    "Label11_1": 87,
    "Label12": 251,
    "Label13": 77,
    "Label13_1": 150,
    "Label14": 151,
    "Label15": 230,
    "Label15_1": 232,
    "Label16": 163,
    "Label2": 270,
    "Label3": 139,
    "Label4": 271,
    "Label5": 272,
    "Label6": 274,
    "Label6_1": 277,
    "Label6_2": 179,
    "Label6_3": 181,
    "Label7": 281,
    "Label8": 273,
    "Label9": 244,
    "Label9_1": 261,
    "Label9_10": 173,
    "Label9_2": 262,
    "Label9_4": 263,
    "Label9_5": 94,
    "Label9_6": 95,
    "Label9_7": 96,
    "Label9_8": 171,
    "Label9_9": 172,
    "LblAppName1": 16,
    "LblAppName3": 189,
    "LblAppName3_1": 51,
    "LblAppName3_2": 63,
    "LblAppName4": 122,
    "logo": 62,
    "logo_1": 50,
    "NextArrow1": 26,
    "NextArrow2": 57,
    "NextArrow2_1": 69,
    "NextArrow6": 35,
    "Price_DataCard3": 212,
    "Price_DataCard4": 136,
    "Price_DataCard7": 99,
    "Quantity_DataCard13": 207,
    "Quantity_DataCard6": 104,
    "Receipts": 48,
    "Rectangle1": 250,
    "Rectangle11": 29,
    "Rectangle2": 162,
    "RectQuickActionBar1": 14,
    "RectQuickActionBar3": 187,
    "RectQuickActionBar4": 120,
    "Sales History": 60,
    "ScannedItem": 72,
    "SearchBox": 242,
    "SearchIcon1": 21,
    "seeInventory": 47,
    "Separator1": 28,
    "Separator1_1": 85,
    "Separator12": 161,
    "Separator2": 59,
    "Separator2_1": 71,
    "Separator6": 38,
    "Separator7": 229,
    "Separator8": 249,
    "SKU_DataCard11": 114,
    "SKU_DataCard14": 192,
    "Slider1": 140,
    "Slider1_1": 86,
    "SoyCandleImage": 3,
    "StarVisible26": 103,
    "StarVisible27": 108,
    "StarVisible28": 113,
    "StarVisible49": 198,
    "StarVisible50": 203,
    "StarVisible51": 213,
    "StarVisible52": 208,
    "StarVisible54": 218,
    "StarVisible55": 193,
    "Subtitle1": 25,
    "Subtitle10": 156,
    "Subtitle2": 58,
    "Subtitle2_1": 70,
    "Subtitle5": 248,
    "Subtitle6": 37,
    "Subtitle6_1": 36,
    "Subtitle7": 227,
    "Subtitle7_1": 228,
    "Test: Adding to Cart": 125,
    "Test: Cart Screen": 222,
    "TextInput1": 276,
    "TextInput1_1": 278,
    "TextInput1_2": 180,
    "TextInput1_3": 182,
    "TextInput2": 231,
    "TextInput3": 6,
    "TextInput3_1": 10,
    "TextSearchBox1": 20,
    "Title1": 24,
    "Title1_1": 81,
    "Title12": 154,
    "Title2": 56,
    "Title2_1": 68,
    "Title5": 34,
    "Title7": 226,
    "Title8": 247,
    "toReceipts": 45,
    "toSales": 44,
    "Up Date Inventory": 97,
    "WholesalePrice_DataCard5": 109,
    "WholesalePrice_DataCard8": 217
  },
  "FunctionParamsInvariantScripts": {},
  "FunctionParamsInvariantScriptsOnInstances": {},
  "HeaderLastSavedDateTimeUTC": "11/16/2022 22:00:43",
  "IsLegacyComponentAllowGlobalScopeCase": false,
  "LocalConnectionIDReferences": {
    "3ede3aa5-3814-40cd-91e0-d6f3385e0167": "\"/providers/microsoft.powerapps/apis/shared_excelonlinebusiness/connections/cfdb8c58d0fd45de8749330830243567\""
  },
  "LocalDatabaseReferencesAsEmpty": false,
  "LocalResourceFileNames": {
    "Lavender Candle": "0001.jpeg",
    "My project-1 (11)": "0002.png",
    "My project-1 (12)": "0003.png",
    "My project-1 (13)": "0004.png",
    "My project-1 (14)": "0005.png",
    "Picture1": "0006.png",
    "soy candle": "0007.jpeg"
  },
  "LocalResourceRootPaths": {
    "Lavender Candle": "https://docserverpwaprodwus.blob.core.windows.net/9bb36d1f-9273-47c8-8ad4-e9d52cb26c7e-1/resource/Assets0Images00001.jpeg?sv=2017-04-17&sr=b&sig=lhiunJLS2nFMydXWtZQZOROpeQzMHGuayyZRMr1u%2Bik%3D&spr=https&se=2022-11-17T20%3A43%3A01Z&sp=r",
    "My project-1 (11)": "https://docserverpwaprodwus.blob.core.windows.net/9bb36d1f-9273-47c8-8ad4-e9d52cb26c7e-1/resource/Assets0Images00002.png?sv=2017-04-17&sr=b&sig=819qg8s7UFYq92kq%2FNt5l0RdJ039Qsw0xu%2FagIglqsU%3D&spr=https&se=2022-11-17T20%3A43%3A01Z&sp=r",
    "My project-1 (12)": "https://docserverpwaprodwus.blob.core.windows.net/9bb36d1f-9273-47c8-8ad4-e9d52cb26c7e-1/resource/Assets0Images00003.png?sv=2017-04-17&sr=b&sig=5ll7JrfPF9U2IFGYBSTZh1MGLpSr%2BdNoT2CbCZZ5BL8%3D&spr=https&se=2022-11-17T20%3A43%3A01Z&sp=r",
    "My project-1 (13)": "https://docserverpwaprodwus.blob.core.windows.net/9bb36d1f-9273-47c8-8ad4-e9d52cb26c7e-1/resource/Assets0Images00004.png?sv=2017-04-17&sr=b&sig=5qARFnPz2hRr0CR07Plpkr7ZFoyhJ6plJoKSgHA2NDg%3D&spr=https&se=2022-11-17T20%3A43%3A01Z&sp=r",
    "My project-1 (14)": "https://docserverpwaprodwus.blob.core.windows.net/9bb36d1f-9273-47c8-8ad4-e9d52cb26c7e-1/resource/Assets0Images00005.png?sv=2017-04-17&sr=b&sig=bLt9yGdYACqe0qIFNAKweOx0902x2bRqlR1MJtSf0r4%3D&spr=https&se=2022-11-17T20%3A43%3A01Z&sp=r",
    "Picture1": "https://docserverpwaprodwus.blob.core.windows.net/9bb36d1f-9273-47c8-8ad4-e9d52cb26c7e-1/resource/Assets0Images00006.png?sv=2017-04-17&sr=b&sig=BHuE6QHM61G3WIr1ER9JQw%2F%2FflDfRVzTr%2F8EsPaeXtQ%3D&spr=https&se=2022-11-17T20%3A43%3A01Z&sp=r",
    "soy candle": "https://docserverpwaprodwus.blob.core.windows.net/9bb36d1f-9273-47c8-8ad4-e9d52cb26c7e-1/resource/Assets0Images00007.jpeg?sv=2017-04-17&sr=b&sig=d5q3jMZzQl2xTXbaHdiVjn6nmzZOvm8lIMv4fea5C38%3D&spr=https&se=2022-11-17T20%3A43%3A01Z&sp=r"
  },
  "OrderComponentMetadata": {
    "635d60e0764844e08f1338d39e15274b": 2,
    "b08eb26c328d40a0a728be4ebe8757be": 1,
    "eed054cea8194bf09981049dfe793d4c": 0
  },
  "OrderComponentTemplate": {
    "635d60e0764844e08f1338d39e15274b": 2,
    "b08eb26c328d40a0a728be4ebe8757be": 1,
    "eed054cea8194bf09981049dfe793d4c": 0
  },
  "OrderDataSource": {
    "collectMultiScan": 5,
    "ComboBoxSample": 0,
    "CustomGallerySample": 1,
    "Data": 2,
    "DropDownSample": 3,
    "ListboxSample": 4,
    "ShoppingCart": 6
  },
  "OrderGroupControls": {
    "Group1": {
      "Label6_2": 2,
      "Label6_3": 3,
      "TextInput1_2": 0,
      "TextInput1_3": 1
    },
    "Group2": {
      "Button4": 2,
      "Button4_1": 3,
      "Label12": 1,
      "Rectangle1": 0
    },
    "Group3": {
      "Button6": 2,
      "Button6_1": 3,
      "Label16": 1,
      "Rectangle2": 0
    }
  },
  "OrderPcfTemplate": {},
  "OrderTemplate": {},
  "OrderXMLTemplate": {
    "arrow": 3,
    "barcodeScanner": 11,
    "button": 7,
    "dropdown": 9,
    "form": 10,
    "gallery": 5,
    "icon": 1,
    "image": 6,
    "label": 2,
    "rectangle": 0,
    "slider": 8,
    "text": 4
  },
  "PublishOrderIndices": {
    "Account_Settings": 11,
    "Add_Item_To_Inventory": 12,
    "Add_to_cart": 60,
    "addItem": 111,
    "App": 0,
    "Arrow2": 99,
    "Arrow2_2": 140,
    "BarcodeScanner1": 37,
    "Body1": 148,
    "Body1_1": 53,
    "Body1_2": 54,
    "Body1_3": 55,
    "Body4": 80,
    "Body4_1": 81,
    "Body4_2": 82,
    "BrowseGallery": 213,
    "BrowseGallery1": 143,
    "BrowseGallery1_1": 50,
    "BrowseGallery1_2": 25,
    "Browsing Gallery": 49,
    "Button1": 17,
    "Button11": 255,
    "Button11_1": 254,
    "Button11_2": 258,
    "Button11_3": 257,
    "Button2": 105,
    "Button2_1": 6,
    "Button3": 238,
    "Button3_1": 59,
    "Button4": 32,
    "Button4_1": 33,
    "Button5": 89,
    "Button6": 87,
    "Button6_1": 88,
    "Button7": 221,
    "Button8": 251,
    "Button9": 252,
    "Cart": 59,
    "Component1": 1,
    "Component1_1": 5,
    "Customer Home Page": 89,
    "Customer page": 1,
    "Customer_Sign_Up": 115,
    "DataCardKey10": 230,
    "DataCardKey12": 224,
    "DataCardKey13": 227,
    "DataCardKey14": 233,
    "DataCardKey38": 200,
    "DataCardKey39": 205,
    "DataCardKey40": 210,
    "DataCardKey43": 196,
    "DataCardKey44": 193,
    "DataCardKey60": 163,
    "DataCardKey61": 168,
    "DataCardKey62": 178,
    "DataCardKey63": 173,
    "DataCardKey65": 183,
    "DataCardKey69": 158,
    "DataCardValue10": 231,
    "DataCardValue12": 225,
    "DataCardValue13": 228,
    "DataCardValue14": 234,
    "DataCardValue38": 201,
    "DataCardValue39": 206,
    "DataCardValue40": 211,
    "DataCardValue43": 197,
    "DataCardValue44": 194,
    "DataCardValue60": 164,
    "DataCardValue61": 169,
    "DataCardValue62": 179,
    "DataCardValue63": 174,
    "DataCardValue65": 184,
    "DataCardValue69": 159,
    "Description_DataCard10": 161,
    "Description_DataCard12": 195,
    "Description_DataCard2": 229,
    "Employee Menu": 132,
    "Employee page": 2,
    "Employee_Sign_Up": 140,
    "ErrorMessage26": 202,
    "ErrorMessage27": 207,
    "ErrorMessage28": 212,
    "ErrorMessage49": 165,
    "ErrorMessage50": 170,
    "ErrorMessage51": 180,
    "ErrorMessage52": 175,
    "ErrorMessage54": 185,
    "ErrorMessage55": 160,
    "FirstScreen": 150,
    "Form1": 222,
    "Form6": 191,
    "Form8": 155,
    "Gallery1": 128,
    "Gallery1_1": 117,
    "Gallery2": 74,
    "Gallery5": 241,
    "galleryTemplate1": 144,
    "galleryTemplate1_1": 51,
    "galleryTemplate1_2": 26,
    "galleryTemplate2": 129,
    "galleryTemplate2_1": 118,
    "galleryTemplate3": 75,
    "galleryTemplate5": 214,
    "galleryTemplate6": 242,
    "Group1": 100,
    "Group2": 23,
    "Group3": 85,
    "Icon1": 127,
    "Icon1_1": 116,
    "Icon10": 38,
    "Icon10_1": 62,
    "Icon10_2": 91,
    "Icon11": 20,
    "Icon11_1": 47,
    "Icon11_2": 71,
    "Icon12": 240,
    "Icon14": 79,
    "Icon2": 34,
    "Icon3": 5,
    "Icon4": 12,
    "Icon5": 16,
    "Icon6": 22,
    "Icon6_1": 108,
    "Icon7": 46,
    "Icon7_1": 70,
    "Icon8": 39,
    "Icon8_2": 63,
    "Icon8_3": 92,
    "Icon9": 40,
    "Icon9_2": 64,
    "Icon9_3": 93,
    "IconAccept2": 153,
    "IconAccept3": 188,
    "IconCancel2": 152,
    "IconCancel3": 187,
    "IconNewItem1": 137,
    "IconRefresh1": 138,
    "IconSortUpDown1": 136,
    "Image_DataCard2": 223,
    "Image1": 4,
    "Image1_1": 45,
    "Image1_3": 69,
    "Image1_4": 98,
    "Image1_5": 107,
    "Image2": 130,
    "Image2_1": 119,
    "Image3": 0,
    "Image4": 259,
    "Image6": 215,
    "Image7": 243,
    "Image8": 49,
    "Image9": 77,
    "Inventory": 154,
    "ItemName_DataCard10": 166,
    "ItemName_DataCard2": 226,
    "ItemWanted": 190,
    "Label1": 239,
    "Label1_1": 3,
    "Label1_10": 106,
    "Label1_11": 113,
    "Label1_12": 124,
    "Label1_2": 19,
    "Label1_3": 36,
    "Label1_4": 97,
    "Label1_6": 44,
    "Label1_7": 61,
    "Label1_8": 68,
    "Label1_9": 90,
    "Label10": 35,
    "Label11": 237,
    "Label11_1": 58,
    "Label12": 31,
    "Label13": 48,
    "Label13_1": 72,
    "Label14": 73,
    "Label15": 248,
    "Label15_1": 250,
    "Label16": 86,
    "Label2": 7,
    "Label3": 235,
    "Label4": 8,
    "Label5": 9,
    "Label6": 11,
    "Label6_1": 14,
    "Label6_2": 101,
    "Label6_3": 103,
    "Label7": 18,
    "Label8": 10,
    "Label9": 24,
    "Label9_1": 41,
    "Label9_10": 96,
    "Label9_2": 42,
    "Label9_4": 43,
    "Label9_5": 65,
    "Label9_6": 66,
    "Label9_7": 67,
    "Label9_8": 94,
    "Label9_9": 95,
    "LblAppName1": 139,
    "LblAppName3": 154,
    "LblAppName3_1": 126,
    "LblAppName3_2": 115,
    "LblAppName4": 189,
    "logo": 114,
    "logo_1": 125,
    "NextArrow1": 147,
    "NextArrow2": 132,
    "NextArrow2_1": 121,
    "NextArrow6": 217,
    "Price_DataCard3": 176,
    "Price_DataCard4": 232,
    "Price_DataCard7": 198,
    "Quantity_DataCard13": 171,
    "Quantity_DataCard6": 203,
    "Receipts": 171,
    "Rectangle1": 30,
    "Rectangle11": 150,
    "Rectangle2": 84,
    "RectQuickActionBar1": 135,
    "RectQuickActionBar3": 151,
    "RectQuickActionBar4": 186,
    "Sales History": 183,
    "ScannedItem": 195,
    "SearchBox": 21,
    "SearchIcon1": 142,
    "seeInventory": 112,
    "Separator1": 149,
    "Separator1_1": 56,
    "Separator12": 83,
    "Separator2": 134,
    "Separator2_1": 123,
    "Separator6": 220,
    "Separator7": 247,
    "Separator8": 29,
    "SKU_DataCard11": 192,
    "SKU_DataCard14": 156,
    "Slider1": 236,
    "Slider1_1": 57,
    "SoyCandleImage": 9,
    "StarVisible26": 199,
    "StarVisible27": 204,
    "StarVisible28": 209,
    "StarVisible49": 162,
    "StarVisible50": 167,
    "StarVisible51": 177,
    "StarVisible52": 172,
    "StarVisible54": 182,
    "StarVisible55": 157,
    "Subtitle1": 146,
    "Subtitle10": 78,
    "Subtitle2": 133,
    "Subtitle2_1": 122,
    "Subtitle5": 28,
    "Subtitle6": 219,
    "Subtitle6_1": 218,
    "Subtitle7": 245,
    "Subtitle7_1": 246,
    "Test: Adding to Cart": 220,
    "Test: Cart Screen": 240,
    "TextInput1": 13,
    "TextInput1_1": 15,
    "TextInput1_2": 102,
    "TextInput1_3": 104,
    "TextInput2": 249,
    "TextInput3": 253,
    "TextInput3_1": 256,
    "TextSearchBox1": 141,
    "Title1": 145,
    "Title1_1": 52,
    "Title12": 76,
    "Title2": 131,
    "Title2_1": 120,
    "Title5": 216,
    "Title7": 244,
    "Title8": 27,
    "toReceipts": 110,
    "toSales": 109,
    "Up Date Inventory": 253,
    "WholesalePrice_DataCard5": 208,
    "WholesalePrice_DataCard8": 181
  },
  "ResourcesJsonIndices": {
    "Image-Lavender Candle": 1,
    "Image-My project-1 (11)": 2,
    "Image-My project-1 (12)": 3,
    "Image-My project-1 (13)": 4,
    "Image-My project-1 (14)": 5,
    "Image-Picture1": 6,
    "Image-SampleImage": 0,
    "Image-soy candle": 7
  },
  "RuleScreenIdWithoutScreen": {},
  "TemplateVersions": {},
  "VolatileProperties": {
    "AnalysisLoadTime": 2.3196888,
    "ControlCount": {
      "635d60e0764844e08f1338d39e15274b": 1,
      "arrow": 2,
      "b08eb26c328d40a0a728be4ebe8757be": 1,
      "barcodeScanner": 1,
      "button": 24,
      "dropdown": 1,
      "eed054cea8194bf09981049dfe793d4c": 1,
      "form": 3,
      "gallery": 8,
      "galleryTemplate": 8,
      "group": 3,
      "icon": 36,
      "image": 15,
      "label": 110,
      "rectangle": 14,
      "screen": 16,
      "slider": 2,
      "text": 18,
      "typedDataCard": 15
    },
    "DeserializationLoadTime": 3.7456448,
    "ErrorCount": 3
  },
  "WasLocalDatabaseReferencesEmpty": true
}