{
  "ComponentIndexes": {
    "Component1": 16,
    "Component1_1": 17,
    "SoyCandleImage": 18
  },
  "ControlUniqueGuids": {},
  "ControlUniqueIds": {
    "Account_Settings": 245,
    "Add_Item_To_Inventory": 246,
    "Add_to_cart": 152,
    "addItem": 109,
    "App": 1,
    "Arrow2": 238,
    "Arrow2_2": 194,
    "BarcodeScanner1": 68,
    "Body1": 202,
    "Body1_1": 145,
    "Body1_2": 146,
    "Body1_3": 147,
    "Body4": 218,
    "Body4_1": 219,
    "Body4_2": 220,
    "BrowseGallery": 94,
    "BrowseGallery1": 197,
    "BrowseGallery1_1": 142,
    "BrowseGallery1_2": 56,
    "Browsing Gallery": 93,
    "Button1": 91,
    "Button11": 8,
    "Button11_1": 7,
    "Button11_2": 12,
    "Button11_3": 11,
    "Button2": 243,
    "Button2_1": 80,
    "Button3": 43,
    "Button3_1": 151,
    "Button4": 63,
    "Button4_1": 64,
    "Button5": 226,
    "Button6": 224,
    "Button6_1": 225,
    "Button7": 102,
    "Button8": 24,
    "Button9": 25,
    "Cart": 205,
    "Component1": 5,
    "Component1_1": 9,
    "Customer Home Page": 50,
    "Customer page": 48,
    "Customer_Sign_Up": 76,
    "DataCardKey10": 35,
    "DataCardKey12": 29,
    "DataCardKey13": 32,
    "DataCardKey14": 38,
    "DataCardKey38": 175,
    "DataCardKey39": 180,
    "DataCardKey40": 185,
    "DataCardKey43": 171,
    "DataCardKey44": 168,
    "DataCardKey60": 259,
    "DataCardKey61": 264,
    "DataCardKey62": 274,
    "DataCardKey63": 269,
    "DataCardKey65": 279,
    "DataCardKey69": 254,
    "DataCardValue10": 36,
    "DataCardValue12": 30,
    "DataCardValue13": 33,
    "DataCardValue14": 39,
    "DataCardValue38": 176,
    "DataCardValue39": 181,
    "DataCardValue40": 186,
    "DataCardValue43": 172,
    "DataCardValue44": 169,
    "DataCardValue60": 260,
    "DataCardValue61": 265,
    "DataCardValue62": 275,
    "DataCardValue63": 270,
    "DataCardValue65": 280,
    "DataCardValue69": 255,
    "Description_DataCard10": 257,
    "Description_DataCard12": 170,
    "Description_DataCard2": 34,
    "Employee Menu": 103,
    "Employee page": 49,
    "Employee_Sign_Up": 235,
    "ErrorMessage26": 177,
    "ErrorMessage27": 182,
    "ErrorMessage28": 187,
    "ErrorMessage49": 261,
    "ErrorMessage50": 266,
    "ErrorMessage51": 276,
    "ErrorMessage52": 271,
    "ErrorMessage54": 281,
    "ErrorMessage55": 256,
    "FirstScreen": 46,
    "Form1": 27,
    "Form6": 166,
    "Form8": 251,
    "Gallery1": 116,
    "Gallery1_1": 128,
    "Gallery2": 212,
    "Gallery5": 14,
    "galleryTemplate1": 198,
    "galleryTemplate1_1": 143,
    "galleryTemplate1_2": 57,
    "galleryTemplate2": 117,
    "galleryTemplate2_1": 129,
    "galleryTemplate3": 213,
    "galleryTemplate5": 95,
    "galleryTemplate6": 15,
    "Group1": 244,
    "Group2": 75,
    "Group3": 234,
    "Icon1": 115,
    "Icon1_1": 127,
    "Icon10": 69,
    "Icon10_1": 154,
    "Icon10_2": 228,
    "Icon11": 52,
    "Icon11_1": 139,
    "Icon11_2": 209,
    "Icon12": 45,
    "Icon14": 217,
    "Icon2": 65,
    "Icon3": 79,
    "Icon4": 86,
    "Icon5": 90,
    "Icon6": 54,
    "Icon6_1": 106,
    "Icon7": 138,
    "Icon7_1": 208,
    "Icon8": 70,
    "Icon8_2": 155,
    "Icon8_3": 229,
    "Icon9": 71,
    "Icon9_2": 156,
    "Icon9_3": 230,
    "IconAccept2": 249,
    "IconAccept3": 163,
    "IconCancel2": 248,
    "IconCancel3": 162,
    "IconNewItem1": 191,
    "IconRefresh1": 192,
    "IconSortUpDown1": 190,
    "Image_DataCard2": 28,
    "Image1": 78,
    "Image1_1": 137,
    "Image1_3": 207,
    "Image1_4": 237,
    "Image1_5": 105,
    "Image2": 118,
    "Image2_1": 130,
    "Image3": 47,
    "Image4": 4,
    "Image6": 96,
    "Image7": 16,
    "Image8": 141,
    "Image9": 215,
    "Inventory": 188,
    "ItemName_DataCard10": 262,
    "ItemName_DataCard2": 31,
    "ItemWanted": 165,
    "Label1": 44,
    "Label1_1": 77,
    "Label1_10": 104,
    "Label1_11": 124,
    "Label1_12": 112,
    "Label1_2": 51,
    "Label1_3": 67,
    "Label1_4": 236,
    "Label1_6": 136,
    "Label1_7": 153,
    "Label1_8": 206,
    "Label1_9": 227,
    "Label10": 66,
    "Label11": 42,
    "Label11_1": 150,
    "Label12": 62,
    "Label13": 140,
    "Label13_1": 210,
    "Label14": 211,
    "Label15": 21,
    "Label15_1": 23,
    "Label16": 223,
    "Label2": 81,
    "Label3": 40,
    "Label4": 82,
    "Label5": 83,
    "Label6": 85,
    "Label6_1": 88,
    "Label6_2": 239,
    "Label6_3": 241,
    "Label7": 92,
    "Label8": 84,
    "Label9": 55,
    "Label9_1": 72,
    "Label9_10": 233,
    "Label9_2": 73,
    "Label9_4": 74,
    "Label9_5": 157,
    "Label9_6": 158,
    "Label9_7": 159,
    "Label9_8": 231,
    "Label9_9": 232,
    "LblAppName1": 193,
    "LblAppName3": 250,
    "LblAppName3_1": 114,
    "LblAppName3_2": 126,
    "LblAppName4": 164,
    "logo": 125,
    "logo_1": 113,
    "NextArrow1": 201,
    "NextArrow2": 120,
    "NextArrow2_1": 132,
    "NextArrow6": 98,
    "Price_DataCard3": 272,
    "Price_DataCard4": 37,
    "Price_DataCard7": 173,
    "Quantity_DataCard13": 267,
    "Quantity_DataCard6": 178,
    "Receipts": 111,
    "Rectangle1": 61,
    "Rectangle11": 204,
    "Rectangle2": 222,
    "RectQuickActionBar1": 189,
    "RectQuickActionBar3": 247,
    "RectQuickActionBar4": 161,
    "Sales History": 123,
    "ScannedItem": 135,
    "SearchBox": 53,
    "SearchIcon1": 196,
    "seeInventory": 110,
    "Separator1": 203,
    "Separator1_1": 148,
    "Separator12": 221,
    "Separator2": 122,
    "Separator2_1": 134,
    "Separator6": 101,
    "Separator7": 20,
    "Separator8": 60,
    "SKU_DataCard11": 167,
    "SKU_DataCard14": 252,
    "Slider1": 41,
    "Slider1_1": 149,
    "SoyCandleImage": 3,
    "StarVisible26": 174,
    "StarVisible27": 179,
    "StarVisible28": 184,
    "StarVisible49": 258,
    "StarVisible50": 263,
    "StarVisible51": 273,
    "StarVisible52": 268,
    "StarVisible54": 278,
    "StarVisible55": 253,
    "Subtitle1": 200,
    "Subtitle10": 216,
    "Subtitle2": 121,
    "Subtitle2_1": 133,
    "Subtitle5": 59,
    "Subtitle6": 100,
    "Subtitle6_1": 99,
    "Subtitle7": 18,
    "Subtitle7_1": 19,
    "Test: Adding to Cart": 26,
    "Test: Cart Screen": 13,
    "TextInput1": 87,
    "TextInput1_1": 89,
    "TextInput1_2": 240,
    "TextInput1_3": 242,
    "TextInput2": 22,
    "TextInput3": 6,
    "TextInput3_1": 10,
    "TextSearchBox1": 195,
    "Title1": 199,
    "Title1_1": 144,
    "Title12": 214,
    "Title2": 119,
    "Title2_1": 131,
    "Title5": 97,
    "Title7": 17,
    "Title8": 58,
    "toReceipts": 108,
    "toSales": 107,
    "Up Date Inventory": 160,
    "WholesalePrice_DataCard5": 183,
    "WholesalePrice_DataCard8": 277
  },
  "FunctionParamsInvariantScripts": {},
  "FunctionParamsInvariantScriptsOnInstances": {},
  "HeaderLastSavedDateTimeUTC": "11/16/2022 22:23:26",
  "IsLegacyComponentAllowGlobalScopeCase": false,
  "LocalConnectionIDReferences": {
    "3ede3aa5-3814-40cd-91e0-d6f3385e0167": "\"/providers/microsoft.powerapps/apis/shared_excelonlinebusiness/connections/cfdb8c58d0fd45de8749330830243567\""
  },
  "LocalDatabaseReferencesAsEmpty": false,
  "LocalResourceFileNames": {
    "Lavender Candle": "0001.jpeg",
    "My project-1 (11)": "0002.png",
    "My project-1 (12)": "0003.png",
    "My project-1 (13)": "0004.png",
    "My project-1 (14)": "0005.png",
    "Picture1": "0006.png",
    "Soy Candle": "8c7606c3-ee7e-4f9e-8900-2a8d0901b2a2.jpeg",
    "soy candle_1": "0007.jpeg"
  },
  "LocalResourceRootPaths": {
    "Lavender Candle": "https://docserverpwaprodwus.blob.core.windows.net/676cad53-05f7-41f6-b947-25df166500a3-1/resource/Assets0Images00001.jpeg?sv=2017-04-17&sr=b&sig=nfbjxxJHffkAwv9AujcyWrX2AcJTL6J4R4QHnX3AuLo%3D&spr=https&se=2022-11-17T22%3A34%3A48Z&sp=r",
    "My project-1 (11)": "https://docserverpwaprodwus.blob.core.windows.net/676cad53-05f7-41f6-b947-25df166500a3-1/resource/Assets0Images00002.png?sv=2017-04-17&sr=b&sig=8eKrT026QZ4nmxrxMTOo1xGETKP9x6NdpybUIdn%2Bt9Q%3D&spr=https&se=2022-11-17T22%3A34%3A48Z&sp=r",
    "My project-1 (12)": "https://docserverpwaprodwus.blob.core.windows.net/676cad53-05f7-41f6-b947-25df166500a3-1/resource/Assets0Images00003.png?sv=2017-04-17&sr=b&sig=rqtKW6zu%2BkYzcdOmhn1VRT81lcwcUmJQ%2BSKqHRh1AME%3D&spr=https&se=2022-11-17T22%3A34%3A48Z&sp=r",
    "My project-1 (13)": "https://docserverpwaprodwus.blob.core.windows.net/676cad53-05f7-41f6-b947-25df166500a3-1/resource/Assets0Images00004.png?sv=2017-04-17&sr=b&sig=rthKbb0u2ybHzFU1BqyduV7J%2FxNHEyh52vwxNwUGvAg%3D&spr=https&se=2022-11-17T22%3A34%3A48Z&sp=r",
    "My project-1 (14)": "https://docserverpwaprodwus.blob.core.windows.net/676cad53-05f7-41f6-b947-25df166500a3-1/resource/Assets0Images00005.png?sv=2017-04-17&sr=b&sig=sX1hRGt4TtgGIRPzt1X8R7QUlbf8JqhQKunBPCbxM2w%3D&spr=https&se=2022-11-17T22%3A34%3A48Z&sp=r",
    "Picture1": "https://docserverpwaprodwus.blob.core.windows.net/676cad53-05f7-41f6-b947-25df166500a3-1/resource/Assets0Images00006.png?sv=2017-04-17&sr=b&sig=%2FXhgEpxf%2Fp0A3Cphrt57B4cmYfTbYDxf7z1gQnm9sOY%3D&spr=https&se=2022-11-17T22%3A34%3A48Z&sp=r",
    "soy candle": "https://docserverpwaprodwus.blob.core.windows.net/676cad53-05f7-41f6-b947-25df166500a3-1/resource/Assets0Images00007.jpeg?sv=2017-04-17&sr=b&sig=Gxg%2BLHAXxXrOC57smovK3AOjS6c6ipCKwBkzENHcjMo%3D&spr=https&se=2022-11-17T22%3A34%3A48Z&sp=r",
    "Soy Candle": "https://docserverpwaprodwus.blob.core.windows.net/676cad53-05f7-41f6-b947-25df166500a3-1/resource/bed6797d-144e-41bf-a993-9726f8ce8e92.jpeg?sv=2017-04-17&sr=b&sig=E1eZmYGpGKzOJGre9o3Tow7nLJiaeBIEbvqUhIRwRno%3D&spr=https&se=2022-11-17T22%3A38%3A16Z&sp=r"
  },
  "OrderComponentMetadata": {
    "635d60e0764844e08f1338d39e15274b": 2,
    "b08eb26c328d40a0a728be4ebe8757be": 1,
    "eed054cea8194bf09981049dfe793d4c": 0
  },
  "OrderComponentTemplate": {
    "635d60e0764844e08f1338d39e15274b": 2,
    "b08eb26c328d40a0a728be4ebe8757be": 1,
    "eed054cea8194bf09981049dfe793d4c": 0
  },
  "OrderDataSource": {
    "collectMultiScan": 5,
    "ComboBoxSample": 0,
    "CustomGallerySample": 1,
    "Data": 2,
    "DropDownSample": 3,
    "ListboxSample": 4,
    "ShoppingCart": 6
  },
  "OrderGroupControls": {
    "Group1": {
      "Label6_2": 2,
      "Label6_3": 3,
      "TextInput1_2": 0,
      "TextInput1_3": 1
    },
    "Group2": {
      "Button4": 2,
      "Button4_1": 3,
      "Label12": 1,
      "Rectangle1": 0
    },
    "Group3": {
      "Button6": 2,
      "Button6_1": 3,
      "Label16": 1,
      "Rectangle2": 0
    }
  },
  "OrderPcfTemplate": {},
  "OrderTemplate": {},
  "OrderXMLTemplate": {
    "arrow": 11,
    "barcodeScanner": 9,
    "button": 5,
    "dropdown": 10,
    "form": 6,
    "gallery": 0,
    "icon": 8,
    "image": 1,
    "label": 2,
    "rectangle": 3,
    "slider": 7,
    "text": 4
  },
  "PublishOrderIndices": {
    "Account_Settings": 11,
    "Add_Item_To_Inventory": 12,
    "Add_to_cart": 60,
    "addItem": 111,
    "App": 0,
    "Arrow2": 99,
    "Arrow2_2": 140,
    "BarcodeScanner1": 37,
    "Body1": 148,
    "Body1_1": 53,
    "Body1_2": 54,
    "Body1_3": 55,
    "Body4": 80,
    "Body4_1": 81,
    "Body4_2": 82,
    "BrowseGallery": 213,
    "BrowseGallery1": 143,
    "BrowseGallery1_1": 50,
    "BrowseGallery1_2": 25,
    "Browsing Gallery": 49,
    "Button1": 17,
    "Button11": 255,
    "Button11_1": 254,
    "Button11_2": 258,
    "Button11_3": 257,
    "Button2": 105,
    "Button2_1": 6,
    "Button3": 238,
    "Button3_1": 59,
    "Button4": 32,
    "Button4_1": 33,
    "Button5": 89,
    "Button6": 87,
    "Button6_1": 88,
    "Button7": 221,
    "Button8": 251,
    "Button9": 252,
    "Cart": 59,
    "Component1": 1,
    "Component1_1": 5,
    "Customer Home Page": 89,
    "Customer page": 1,
    "Customer_Sign_Up": 115,
    "DataCardKey10": 230,
    "DataCardKey12": 224,
    "DataCardKey13": 227,
    "DataCardKey14": 233,
    "DataCardKey38": 200,
    "DataCardKey39": 205,
    "DataCardKey40": 210,
    "DataCardKey43": 196,
    "DataCardKey44": 193,
    "DataCardKey60": 163,
    "DataCardKey61": 168,
    "DataCardKey62": 178,
    "DataCardKey63": 173,
    "DataCardKey65": 183,
    "DataCardKey69": 158,
    "DataCardValue10": 231,
    "DataCardValue12": 225,
    "DataCardValue13": 228,
    "DataCardValue14": 234,
    "DataCardValue38": 201,
    "DataCardValue39": 206,
    "DataCardValue40": 211,
    "DataCardValue43": 197,
    "DataCardValue44": 194,
    "DataCardValue60": 164,
    "DataCardValue61": 169,
    "DataCardValue62": 179,
    "DataCardValue63": 174,
    "DataCardValue65": 184,
    "DataCardValue69": 159,
    "Description_DataCard10": 161,
    "Description_DataCard12": 195,
    "Description_DataCard2": 229,
    "Employee Menu": 132,
    "Employee page": 2,
    "Employee_Sign_Up": 140,
    "ErrorMessage26": 202,
    "ErrorMessage27": 207,
    "ErrorMessage28": 212,
    "ErrorMessage49": 165,
    "ErrorMessage50": 170,
    "ErrorMessage51": 180,
    "ErrorMessage52": 175,
    "ErrorMessage54": 185,
    "ErrorMessage55": 160,
    "FirstScreen": 150,
    "Form1": 222,
    "Form6": 191,
    "Form8": 155,
    "Gallery1": 128,
    "Gallery1_1": 117,
    "Gallery2": 74,
    "Gallery5": 241,
    "galleryTemplate1": 144,
    "galleryTemplate1_1": 51,
    "galleryTemplate1_2": 26,
    "galleryTemplate2": 129,
    "galleryTemplate2_1": 118,
    "galleryTemplate3": 75,
    "galleryTemplate5": 214,
    "galleryTemplate6": 242,
    "Group1": 100,
    "Group2": 23,
    "Group3": 85,
    "Icon1": 127,
    "Icon1_1": 116,
    "Icon10": 38,
    "Icon10_1": 62,
    "Icon10_2": 91,
    "Icon11": 20,
    "Icon11_1": 47,
    "Icon11_2": 71,
    "Icon12": 240,
    "Icon14": 79,
    "Icon2": 34,
    "Icon3": 5,
    "Icon4": 12,
    "Icon5": 16,
    "Icon6": 22,
    "Icon6_1": 108,
    "Icon7": 46,
    "Icon7_1": 70,
    "Icon8": 39,
    "Icon8_2": 63,
    "Icon8_3": 92,
    "Icon9": 40,
    "Icon9_2": 64,
    "Icon9_3": 93,
    "IconAccept2": 153,
    "IconAccept3": 188,
    "IconCancel2": 152,
    "IconCancel3": 187,
    "IconNewItem1": 137,
    "IconRefresh1": 138,
    "IconSortUpDown1": 136,
    "Image_DataCard2": 223,
    "Image1": 4,
    "Image1_1": 45,
    "Image1_3": 69,
    "Image1_4": 98,
    "Image1_5": 107,
    "Image2": 130,
    "Image2_1": 119,
    "Image3": 0,
    "Image4": 259,
    "Image6": 215,
    "Image7": 243,
    "Image8": 49,
    "Image9": 77,
    "Inventory": 154,
    "ItemName_DataCard10": 166,
    "ItemName_DataCard2": 226,
    "ItemWanted": 190,
    "Label1": 239,
    "Label1_1": 3,
    "Label1_10": 106,
    "Label1_11": 113,
    "Label1_12": 124,
    "Label1_2": 19,
    "Label1_3": 36,
    "Label1_4": 97,
    "Label1_6": 44,
    "Label1_7": 61,
    "Label1_8": 68,
    "Label1_9": 90,
    "Label10": 35,
    "Label11": 237,
    "Label11_1": 58,
    "Label12": 31,
    "Label13": 48,
    "Label13_1": 72,
    "Label14": 73,
    "Label15": 248,
    "Label15_1": 250,
    "Label16": 86,
    "Label2": 7,
    "Label3": 235,
    "Label4": 8,
    "Label5": 9,
    "Label6": 11,
    "Label6_1": 14,
    "Label6_2": 101,
    "Label6_3": 103,
    "Label7": 18,
    "Label8": 10,
    "Label9": 24,
    "Label9_1": 41,
    "Label9_10": 96,
    "Label9_2": 42,
    "Label9_4": 43,
    "Label9_5": 65,
    "Label9_6": 66,
    "Label9_7": 67,
    "Label9_8": 94,
    "Label9_9": 95,
    "LblAppName1": 139,
    "LblAppName3": 154,
    "LblAppName3_1": 126,
    "LblAppName3_2": 115,
    "LblAppName4": 189,
    "logo": 114,
    "logo_1": 125,
    "NextArrow1": 147,
    "NextArrow2": 132,
    "NextArrow2_1": 121,
    "NextArrow6": 217,
    "Price_DataCard3": 176,
    "Price_DataCard4": 232,
    "Price_DataCard7": 198,
    "Quantity_DataCard13": 171,
    "Quantity_DataCard6": 203,
    "Receipts": 171,
    "Rectangle1": 30,
    "Rectangle11": 150,
    "Rectangle2": 84,
    "RectQuickActionBar1": 135,
    "RectQuickActionBar3": 151,
    "RectQuickActionBar4": 186,
    "Sales History": 183,
    "ScannedItem": 195,
    "SearchBox": 21,
    "SearchIcon1": 142,
    "seeInventory": 112,
    "Separator1": 149,
    "Separator1_1": 56,
    "Separator12": 83,
    "Separator2": 134,
    "Separator2_1": 123,
    "Separator6": 220,
    "Separator7": 247,
    "Separator8": 29,
    "SKU_DataCard11": 192,
    "SKU_DataCard14": 156,
    "Slider1": 236,
    "Slider1_1": 57,
    "SoyCandleImage": 9,
    "StarVisible26": 199,
    "StarVisible27": 204,
    "StarVisible28": 209,
    "StarVisible49": 162,
    "StarVisible50": 167,
    "StarVisible51": 177,
    "StarVisible52": 172,
    "StarVisible54": 182,
    "StarVisible55": 157,
    "Subtitle1": 146,
    "Subtitle10": 78,
    "Subtitle2": 133,
    "Subtitle2_1": 122,
    "Subtitle5": 28,
    "Subtitle6": 219,
    "Subtitle6_1": 218,
    "Subtitle7": 245,
    "Subtitle7_1": 246,
    "Test: Adding to Cart": 220,
    "Test: Cart Screen": 240,
    "TextInput1": 13,
    "TextInput1_1": 15,
    "TextInput1_2": 102,
    "TextInput1_3": 104,
    "TextInput2": 249,
    "TextInput3": 253,
    "TextInput3_1": 256,
    "TextSearchBox1": 141,
    "Title1": 145,
    "Title1_1": 52,
    "Title12": 76,
    "Title2": 131,
    "Title2_1": 120,
    "Title5": 216,
    "Title7": 244,
    "Title8": 27,
    "toReceipts": 110,
    "toSales": 109,
    "Up Date Inventory": 253,
    "WholesalePrice_DataCard5": 208,
    "WholesalePrice_DataCard8": 181
  },
  "ResourcesJsonIndices": {
    "Image-Lavender Candle": 1,
    "Image-My project-1 (11)": 2,
    "Image-My project-1 (12)": 3,
    "Image-My project-1 (13)": 4,
    "Image-My project-1 (14)": 5,
    "Image-Picture1": 6,
    "Image-SampleImage": 0,
    "Image-Soy Candle": 8,
    "Image-soy candle_1": 7
  },
  "RuleScreenIdWithoutScreen": {},
  "TemplateVersions": {},
  "VolatileProperties": {
    "AnalysisLoadTime": 1.9181241,
    "ControlCount": {
      "635d60e0764844e08f1338d39e15274b": 1,
      "arrow": 2,
      "b08eb26c328d40a0a728be4ebe8757be": 1,
      "barcodeScanner": 1,
      "button": 24,
      "dropdown": 1,
      "eed054cea8194bf09981049dfe793d4c": 1,
      "form": 3,
      "gallery": 8,
      "galleryTemplate": 8,
      "group": 3,
      "icon": 36,
      "image": 15,
      "label": 110,
      "rectangle": 14,
      "screen": 16,
      "slider": 2,
      "text": 18,
      "typedDataCard": 15
    },
    "DeserializationLoadTime": 3.2944279,
    "ErrorCount": 3
  },
  "WasLocalDatabaseReferencesEmpty": true
}